jupyter_kernel_agent-1.2.2.dist-info/licenses/LICENSE
kernel_agent/__init__.py
kernel_agent/cli.py
kernel_agent/kernel.py
kernel_agent/schemas.py
kernel_agent/utils.py
jupyter_kernel_agent-1.2.2.dist-info/METADATA
jupyter_kernel_agent-1.2.2.dist-info/WHEEL
jupyter_kernel_agent-1.2.2.dist-info/entry_points.txt
jupyter_kernel_agent-1.2.2.dist-info/top_level.txt
jupyter_kernel_agent-1.2.2.dist-info/RECORD
