Metadata-Version: 2.4
Name: jupyter-kernel-agent
Version: 1.2.2
Summary: An agent to bring cluster kernel to local
Author-email: Leo <leoustc@icloud.com>
Requires-Python: >=3.8
License-File: LICENSE
Requires-Dist: ipykernel>=6.0
Requires-Dist: jupyter_client>=8.0
Requires-Dist: requests>=2.31
Dynamic: license-file
